autosend/__init__.py
autosend/client.py
autosend/errors.py
autosend/resources/contacts.py
autosend/resources/sending.py
tests/contacts_test.py
tests/sending_test.py
autosend_shreya_sdk-1.1.0.dist-info/METADATA
autosend_shreya_sdk-1.1.0.dist-info/WHEEL
autosend_shreya_sdk-1.1.0.dist-info/top_level.txt
autosend_shreya_sdk-1.1.0.dist-info/RECORD
