Metadata-Version: 2.4
Name: autosend-shreya-sdk
Version: 1.1.0
Summary: Unofficial Autosend Email API SDK (Python) by Shreya Pandey
Author-email: Shreya Pandey <shreyap2702@gmail.com>
Project-URL: Homepage, https://github.com/shreyap2702/autosend-python-sdk
Project-URL: Repository, https://github.com/shreyap2702/autosend-python-sdk
Requires-Python: >=3.10
Requires-Dist: requests>=2.32.5
